[
  {
    "filename": "Rest Break SOP.docx",
    "paragraph": 1,
    "type": "text",
    "content": "Scottish Ambulance Service\n\nManagement of Rest Breaks\n\nStandard Operating Procedure – Test of Change V1.0",
    "keywords": [
      "scottish",
      "ambulance",
      "service",
      "management",
      "rest",
      "breaks",
      "standard",
      "operating",
      "procedure",
      "test",
      "change"
    ]
  },
  {
    "filename": "Rest Break SOP.docx",
    "paragraph": 2,
    "type": "text",
    "content": "Aim \n\nTo ensure appropriate and effective rest break management of all resources booked onto the C3 System for deployment and to improve rest break compliance, working to the principle that nobody should work more than 6 hours without a break.",
    "keywords": [
      "ensure",
      "appropriate",
      "effective",
      "rest",
      "break",
      "management",
      "resources",
      "booked",
      "onto",
      "system",
      "deployment",
      "improve",
      "rest",
      "break",
      "compliance",
      "working",
      "principle",
      "nobody",
      "should",
      "work",
      "more",
      "than",
      "hours",
      "without",
      "break"
    ]
  },
  {
    "filename": "Rest Break SOP.docx",
    "paragraph": 3,
    "type": "text",
    "content": "Definition of a Rest Break \n\nThe definition of a rest break is a short period of time not less than 20 mins, undisturbed, which should not be taken at the commencement or end of the working day, where an employee is able to stop and relax, use facilities, or simply take time to clear their heads, therefore pause, and recharge.",
    "keywords": [
      "definition",
      "rest",
      "break",
      "definition",
      "rest",
      "break",
      "short",
      "period",
      "time",
      "less",
      "than",
      "mins",
      "undisturbed",
      "which",
      "should",
      "taken",
      "commencement",
      "working",
      "where",
      "employee",
      "able",
      "stop",
      "relax",
      "facilities",
      "simply",
      "take",
      "time",
      "clear",
      "their",
      "heads",
      "therefore",
      "pause",
      "recharge"
    ]
  },
  {
    "filename": "Rest Break SOP.docx",
    "paragraph": 4,
    "type": "text",
    "content": "Application \n\nDispatchers within the Ambulance Control Centres (ACC) will be responsible for the consistent application of this Standard Operating Procedure.\n\nThis applies to all operational colleagues booked onto the C3 system.",
    "keywords": [
      "application",
      "dispatchers",
      "within",
      "ambulance",
      "control",
      "centres",
      "responsible",
      "consistent",
      "application",
      "standard",
      "operating",
      "procedure",
      "applies",
      "operational",
      "colleagues",
      "booked",
      "onto",
      "system"
    ]
  },
  {
    "filename": "Rest Break SOP.docx",
    "paragraph": 5,
    "type": "text",
    "content": "Policy \n\nThe Service gives an absolute commitment to provide rest breaks to all staff to whom this agreement applies. The SOP will apply to all Scottish Ambulance Service colleagues booked onto the C3 system for deployment. \n\nThis SOP looks to, organisationally, support Dispatchers within their decision making to balance operational colleague welfare and patient safety.  To assist in this process, the following procedure should be followed: \n\nAll rest breaks are agreed through partnership and identified through the C3 system. \n\nIf a crew are split due to skill mix or doubled up for any reason, the dispatcher and crew should mutually agree on what shift code they will be using to book on (system accepts only 1 code) and the rest break window best suited to both parties. \n\nWhere a crew are booking on late due to lie in, fatigue, compensatory rest or previous shift overrun, the dispatcher and crew should mutually agree a shift code which reflects the shift now being worked rounded up to the nearest hour. \n\nClarifier: it is important that we allocate a rest break window and length against the shift being worked. This prevents a crew booking on and being immediately due a break. \n\nExample: a crew rostered 0700/1900 however booking on at 0930 due to a previous shift overrun - The crew should be booked onto a 0900/1900 shift which allows for a 38 minute rest break between the 4th and 6th hour of the worked shift.  \n\nIf a crew chooses to rest at a location other than their home station, they will only be assigned ILT and amber codes until they have returned to their normal response area. This will help ensure resources return to their areas after a rest break. \n\nClarifier – it is important that we try as best we can to return a rested crew to their base location for local cover, however if closest to an ILT or amber call they should still be allocated to this incident for patient safety.",
    "keywords": [
      "policy",
      "service",
      "gives",
      "absolute",
      "commitment",
      "provide",
      "rest",
      "breaks",
      "staff",
      "whom",
      "agreement",
      "applies",
      "apply",
      "scottish",
      "ambulance",
      "service",
      "colleagues",
      "booked",
      "onto",
      "system",
      "deployment",
      "looks",
      "organisationally",
      "support",
      "dispatchers",
      "within",
      "their",
      "decision",
      "making",
      "balance",
      "operational",
      "colleague",
      "welfare",
      "patient",
      "safety",
      "assist",
      "process",
      "following",
      "procedure",
      "should",
      "followed",
      "rest",
      "breaks",
      "agreed",
      "through",
      "partnership",
      "identified",
      "through",
      "system",
      "crew",
      "split",
      "skill",
      "doubled",
      "reason",
      "dispatcher",
      "crew",
      "should",
      "mutually",
      "agree",
      "what",
      "shift",
      "code",
      "they",
      "using",
      "book",
      "system",
      "accepts",
      "only",
      "code",
      "rest",
      "break",
      "window",
      "best",
      "suited",
      "both",
      "parties",
      "where",
      "crew",
      "booking",
      "late",
      "fatigue",
      "compensatory",
      "rest",
      "previous",
      "shift",
      "overrun",
      "dispatcher",
      "crew",
      "should",
      "mutually",
      "agree",
      "shift",
      "code",
      "which",
      "reflects",
      "shift",
      "being",
      "worked",
      "rounded",
      "nearest",
      "hour",
      "clarifier",
      "important",
      "allocate",
      "rest",
      "break",
      "window",
      "length",
      "against",
      "shift",
      "being",
      "worked",
      "prevents",
      "crew",
      "booking",
      "being",
      "immediately",
      "break",
      "example",
      "crew",
      "rostered",
      "07001900",
      "however",
      "booking",
      "0930",
      "previous",
      "shift",
      "overrun",
      "crew",
      "should",
      "booked",
      "onto",
      "09001900",
      "shift",
      "which",
      "allows",
      "minute",
      "rest",
      "break",
      "between",
      "hour",
      "worked",
      "shift",
      "crew",
      "chooses",
      "rest",
      "location",
      "other",
      "than",
      "their",
      "home",
      "station",
      "they",
      "only",
      "assigned",
      "amber",
      "codes",
      "until",
      "they",
      "returned",
      "their",
      "normal",
      "response",
      "area",
      "help",
      "ensure",
      "resources",
      "return",
      "their",
      "areas",
      "after",
      "rest",
      "break",
      "clarifier",
      "important",
      "best",
      "return",
      "rested",
      "crew",
      "their",
      "base",
      "location",
      "local",
      "cover",
      "however",
      "closest",
      "amber",
      "call",
      "they",
      "should",
      "still",
      "allocated",
      "incident",
      "patient",
      "safety"
    ]
  },
  {
    "filename": "Rest Break SOP.docx",
    "paragraph": 6,
    "type": "text",
    "content": "Rest Break Windows\n\n8-hour shift – 1x RB window between 3rd and 5th hour\n\n10-hour shift – 1x RB window between 4th and 6th hour \n\n12-hour shift - 2x Rest Breaks (1x 25 mins and 1x 20 mins)\n\nWindows: 3rd to 5th hour and 7th to 9th hour\n\nThe national Rest Break windows and durations, agreed in partnership, are outlined in the table below:\n\nShift Length \n\nNo of Breaks \n\nWindow \n\nPeriod Entitlement \n\nPeriod Lengths \n\n08 Hour \n\n1 \n\n3rd& 5th Hour \n\n30 \n\n30 \n\n10 Hour \n\n1 \n\n4th& 6th Hour \n\n38 \n\n38 \n\n12 Hour \n\n2 \n\n3rd& 5th Hour and\n\n7th & 9th Hour \n\n45 \n\n25 +20  \n\nClarifier: These shift codes and windows are the only ones approved, all other shift codes will be removed – e.g a crew cannot opt for 1 break in a 12 hour shift any more.  Any requests for new shift codes or windows must be agreed in partnership and follow the new shift code request process",
    "keywords": [
      "rest",
      "break",
      "windows",
      "8hour",
      "shift",
      "window",
      "between",
      "hour",
      "10hour",
      "shift",
      "window",
      "between",
      "hour",
      "12hour",
      "shift",
      "rest",
      "breaks",
      "mins",
      "mins",
      "windows",
      "hour",
      "hour",
      "national",
      "rest",
      "break",
      "windows",
      "durations",
      "agreed",
      "partnership",
      "outlined",
      "table",
      "below",
      "shift",
      "length",
      "breaks",
      "window",
      "period",
      "entitlement",
      "period",
      "lengths",
      "hour",
      "hour",
      "hour",
      "hour",
      "hour",
      "hour",
      "hour",
      "clarifier",
      "these",
      "shift",
      "codes",
      "windows",
      "only",
      "ones",
      "approved",
      "other",
      "shift",
      "codes",
      "removed",
      "crew",
      "cannot",
      "break",
      "hour",
      "shift",
      "more",
      "requests",
      "shift",
      "codes",
      "windows",
      "must",
      "agreed",
      "partnership",
      "follow",
      "shift",
      "code",
      "request",
      "process"
    ]
  },
  {
    "filename": "Rest Break SOP.docx",
    "paragraph": 7,
    "type": "text",
    "content": "Procedure \n\n\n\nBefore and throughout rest period windows, operational crews will be protected from some incidents to prioritise a rest period as early as possible. Dispatchers within the Ambulance Control Centres will make every effort to allocate rest breaks at the earliest opportunity when rest period windows open in line with rest break windows. Crews will be returned to station as quickly as possible and should take the most direct route.\n\nTo ensure an appropriate response is maintained to the most time critical patients and major incidents, all staff as listed above will be required to remain available throughout their shift (except in the case of Special Break protection) for the following: \n\nAll coded, clinically triaged ILT (Purple/Red) incidents\n\nMajor Incidents\n\nSORT PDAs (SORT Teams only) \n\nNote – clinically triaged incidents are incidents coded using MPDS by call handlers, or outcome codes by the Integrated Clinical Hub or Specialist Service Desk. \n\nThis is described in the procedures below:",
    "keywords": [
      "procedure",
      "before",
      "throughout",
      "rest",
      "period",
      "windows",
      "operational",
      "crews",
      "protected",
      "some",
      "incidents",
      "prioritise",
      "rest",
      "period",
      "early",
      "possible",
      "dispatchers",
      "within",
      "ambulance",
      "control",
      "centres",
      "make",
      "every",
      "effort",
      "allocate",
      "rest",
      "breaks",
      "earliest",
      "opportunity",
      "rest",
      "period",
      "windows",
      "open",
      "line",
      "rest",
      "break",
      "windows",
      "crews",
      "returned",
      "station",
      "quickly",
      "possible",
      "should",
      "take",
      "most",
      "direct",
      "route",
      "ensure",
      "appropriate",
      "response",
      "maintained",
      "most",
      "time",
      "critical",
      "patients",
      "major",
      "incidents",
      "staff",
      "listed",
      "above",
      "required",
      "remain",
      "available",
      "throughout",
      "their",
      "shift",
      "except",
      "case",
      "special",
      "break",
      "protection",
      "following",
      "coded",
      "clinically",
      "triaged",
      "purplered",
      "incidents",
      "major",
      "incidents",
      "sort",
      "pdas",
      "sort",
      "teams",
      "only",
      "note",
      "clinically",
      "triaged",
      "incidents",
      "incidents",
      "coded",
      "using",
      "mpds",
      "call",
      "handlers",
      "outcome",
      "codes",
      "integrated",
      "clinical",
      "specialist",
      "service",
      "desk",
      "described",
      "procedures",
      "below"
    ]
  },
  {
    "filename": "Rest Break SOP.docx",
    "paragraph": 8,
    "type": "text",
    "content": "Protection Prior to a Rest Break Window: \n\nWhere a crew are on station, and in the 15 minutes prior to a rest period window opening the crew will have the opportunity to request their rest period early.\n\nClarifier – the dispatcher should not offer this, it should be requested by the crew.\n\nA crew will not be allocated to a TIMED ADMISSION or ROUTINE CALL 1 hour prior to the rest break window opening. \n\nA crew will not be allocated to a YELLOW call 30 minutes prior to a rest break window opening. \n\nAdditional notes on protection prior to rest break window: it is important that we try and rest crews as early as possible to prevent later unavailability, Timed Admission and Yellow protection prior to a rest break increase the opportunity to rest a crew as early as possible within the window.",
    "keywords": [
      "protection",
      "prior",
      "rest",
      "break",
      "window",
      "where",
      "crew",
      "station",
      "minutes",
      "prior",
      "rest",
      "period",
      "window",
      "opening",
      "crew",
      "opportunity",
      "request",
      "their",
      "rest",
      "period",
      "early",
      "clarifier",
      "dispatcher",
      "should",
      "offer",
      "should",
      "requested",
      "crew",
      "crew",
      "allocated",
      "timed",
      "admission",
      "routine",
      "call",
      "hour",
      "prior",
      "rest",
      "break",
      "window",
      "opening",
      "crew",
      "allocated",
      "yellow",
      "call",
      "minutes",
      "prior",
      "rest",
      "break",
      "window",
      "opening",
      "additional",
      "notes",
      "protection",
      "prior",
      "rest",
      "break",
      "window",
      "important",
      "rest",
      "crews",
      "early",
      "possible",
      "prevent",
      "later",
      "unavailability",
      "timed",
      "admission",
      "yellow",
      "protection",
      "prior",
      "rest",
      "break",
      "increase",
      "opportunity",
      "rest",
      "crew",
      "early",
      "possible",
      "within",
      "window"
    ]
  },
  {
    "filename": "Rest Break SOP.docx",
    "paragraph": 9,
    "type": "text",
    "content": "Protection During a Rest Break Window:\n\nWhere a staff member requests a break at the location they are currently in, e.g. at the nearest ambulance station or at hospital, this should be agreed, and the crew should be booked off. \n\nA crew will not be allocated to a TIMED ADMISSION or ROUTINE CALL until the rest break is complete.\n\nA crew will not be allocated to a YELLOW until the rest break is complete. \n\nIf a crew reach the mid-point of the rest break window without commencing their rest break, they will no longer be allocated to an AMBER until the rest break is complete. \n\nCrews will only be allocated to a PURPLE or RED inter facility transfer where there is no other resource immediately available. In practice this means where the alternative resource is under 10 mins away.",
    "keywords": [
      "protection",
      "during",
      "rest",
      "break",
      "window",
      "where",
      "staff",
      "member",
      "requests",
      "break",
      "location",
      "they",
      "currently",
      "nearest",
      "ambulance",
      "station",
      "hospital",
      "should",
      "agreed",
      "crew",
      "should",
      "booked",
      "crew",
      "allocated",
      "timed",
      "admission",
      "routine",
      "call",
      "until",
      "rest",
      "break",
      "complete",
      "crew",
      "allocated",
      "yellow",
      "until",
      "rest",
      "break",
      "complete",
      "crew",
      "reach",
      "midpoint",
      "rest",
      "break",
      "window",
      "without",
      "commencing",
      "their",
      "rest",
      "break",
      "they",
      "longer",
      "allocated",
      "amber",
      "until",
      "rest",
      "break",
      "complete",
      "crews",
      "only",
      "allocated",
      "purple",
      "inter",
      "facility",
      "transfer",
      "where",
      "there",
      "other",
      "resource",
      "immediately",
      "available",
      "practice",
      "means",
      "where",
      "alternative",
      "resource",
      "under",
      "mins",
      "away"
    ]
  },
  {
    "filename": "Rest Break SOP.docx",
    "paragraph": 10,
    "type": "text",
    "content": "Protection After a Rest Break Window \n\nA crew will not be allocated to a TIMED ADMISSION or ROUTINE CALL until the rest break is complete.  \n\nA crew will not be allocated to a YELLOW until the rest break is complete. \n\nA crew will not be allocated to an AMBER incident until the rest break is complete.\n\nCrews must be disturbed for an ILT call (if they are the nearest and most appropriate resource), but will only be allocated to a PURPLE or RED inter facility transfer where there is no other resource immediately available.\n\nNOTE: An interfacility transfer is also known as a hospital-to-hospital transfer.",
    "keywords": [
      "protection",
      "after",
      "rest",
      "break",
      "window",
      "crew",
      "allocated",
      "timed",
      "admission",
      "routine",
      "call",
      "until",
      "rest",
      "break",
      "complete",
      "crew",
      "allocated",
      "yellow",
      "until",
      "rest",
      "break",
      "complete",
      "crew",
      "allocated",
      "amber",
      "incident",
      "until",
      "rest",
      "break",
      "complete",
      "crews",
      "must",
      "disturbed",
      "call",
      "they",
      "nearest",
      "most",
      "appropriate",
      "resource",
      "only",
      "allocated",
      "purple",
      "inter",
      "facility",
      "transfer",
      "where",
      "there",
      "other",
      "resource",
      "immediately",
      "available",
      "note",
      "interfacility",
      "transfer",
      "also",
      "known",
      "hospitaltohospital",
      "transfer"
    ]
  },
  {
    "filename": "Rest Break SOP.docx",
    "paragraph": 11,
    "type": "text",
    "content": "Special Break Protection\n\nA Special Break is irrefusable in two scenarios within a shift:\n\nIf a crew have not been rested by at the end of the first rest break window, they can request a Special Break for additional protection. Normally, this means they take the remaining rest break time owed during the shift.\n\nException: If taking the full balance would leave the crew with more than 6 hours left to work, they only take the first break balance now, and the second break will happen in the next window. \n\nA Special Break can also be requested if it has been over 6 hours since the end of the last rest break, and the crew still have break time owed.\n\nOnce special break protection is applied the crew will only be sent to purple coded incidents or major incidents until their owed break time is complete.\n\nA graphic of these levels of protection can be found below:",
    "keywords": [
      "special",
      "break",
      "protection",
      "special",
      "break",
      "irrefusable",
      "scenarios",
      "within",
      "shift",
      "crew",
      "been",
      "rested",
      "first",
      "rest",
      "break",
      "window",
      "they",
      "request",
      "special",
      "break",
      "additional",
      "protection",
      "normally",
      "means",
      "they",
      "take",
      "remaining",
      "rest",
      "break",
      "time",
      "owed",
      "during",
      "shift",
      "exception",
      "taking",
      "full",
      "balance",
      "would",
      "leave",
      "crew",
      "more",
      "than",
      "hours",
      "left",
      "work",
      "they",
      "only",
      "take",
      "first",
      "break",
      "balance",
      "second",
      "break",
      "happen",
      "next",
      "window",
      "special",
      "break",
      "also",
      "requested",
      "been",
      "over",
      "hours",
      "since",
      "last",
      "rest",
      "break",
      "crew",
      "still",
      "break",
      "time",
      "owed",
      "once",
      "special",
      "break",
      "protection",
      "applied",
      "crew",
      "only",
      "sent",
      "purple",
      "coded",
      "incidents",
      "major",
      "incidents",
      "until",
      "their",
      "owed",
      "break",
      "time",
      "complete",
      "graphic",
      "these",
      "levels",
      "protection",
      "found",
      "below"
    ],
    "image": "images/TestImage.png"
  },
  {
    "filename": "Rest Break SOP.docx",
    "paragraph": 12,
    "type": "text",
    "content": "Rest Break Disturbances \n\nA crew will only be disturbed from a rest break for a coded, clinically triaged ILT or a Major Incident. \n\nDispatchers will make every effort to allocate or divert another resource, however, where there is no other response immediately available, a crew will have to be disturbed. In practice this means where the alternative resource is under 10 mins away.\n\nIf a crew has been disturbed when on a rest break, once clear from the incident, a crew will only be sent to purple coded incidents or major incidents until their owed break time is complete. \n\nException: If taking the full balance would leave the crew with more than 6 hours left to work, they only take the first break balance now, and the second break will happen in the next window.",
    "keywords": [
      "rest",
      "break",
      "disturbances",
      "crew",
      "only",
      "disturbed",
      "rest",
      "break",
      "coded",
      "clinically",
      "triaged",
      "major",
      "incident",
      "dispatchers",
      "make",
      "every",
      "effort",
      "allocate",
      "divert",
      "another",
      "resource",
      "however",
      "where",
      "there",
      "other",
      "response",
      "immediately",
      "available",
      "crew",
      "disturbed",
      "practice",
      "means",
      "where",
      "alternative",
      "resource",
      "under",
      "mins",
      "away",
      "crew",
      "been",
      "disturbed",
      "rest",
      "break",
      "once",
      "clear",
      "incident",
      "crew",
      "only",
      "sent",
      "purple",
      "coded",
      "incidents",
      "major",
      "incidents",
      "until",
      "their",
      "owed",
      "break",
      "time",
      "complete",
      "exception",
      "taking",
      "full",
      "balance",
      "would",
      "leave",
      "crew",
      "more",
      "than",
      "hours",
      "left",
      "work",
      "they",
      "only",
      "take",
      "first",
      "break",
      "balance",
      "second",
      "break",
      "happen",
      "next",
      "window"
    ]
  },
  {
    "filename": "Rest Break SOP.docx",
    "paragraph": 13,
    "type": "text",
    "content": "Special Break Disturbances \n\nIn the event a crew request a special break and are disturbed for a purple coded incident or major incident, once clear from the incident the crew will automatically be made unavailable until the owed break time is complete. \n\n\n\nNote: If there are two vehicles available on a station, one on a rest break and one in the final hour of their duty, then the crew on rest break should be allocated the call and the rest break SOP applied.",
    "keywords": [
      "special",
      "break",
      "disturbances",
      "event",
      "crew",
      "request",
      "special",
      "break",
      "disturbed",
      "purple",
      "coded",
      "incident",
      "major",
      "incident",
      "once",
      "clear",
      "incident",
      "crew",
      "automatically",
      "made",
      "unavailable",
      "until",
      "owed",
      "break",
      "time",
      "complete",
      "note",
      "there",
      "vehicles",
      "available",
      "station",
      "rest",
      "break",
      "final",
      "hour",
      "their",
      "duty",
      "then",
      "crew",
      "rest",
      "break",
      "should",
      "allocated",
      "call",
      "rest",
      "break",
      "applied"
    ]
  }
]